odoo/addons/mail_format_with_parent/LICENSE
odoo/addons/mail_format_with_parent/README.rst
odoo/addons/mail_format_with_parent/__init__.py
odoo/addons/mail_format_with_parent/__manifest__.py
odoo/addons/mail_format_with_parent/images/screen.png
odoo/addons/mail_format_with_parent/models/__init__.py
odoo/addons/mail_format_with_parent/models/mail_mail.py
odoo/addons/mail_format_with_parent/models/res_partner.py
odoo/addons/mail_format_with_parent/static/description/icon.png
odoo/addons/mail_format_with_parent/static/description/index.html
odoo_addon_mail_format_with_parent-18.0.1.0.0.dist-info/METADATA
odoo_addon_mail_format_with_parent-18.0.1.0.0.dist-info/WHEEL
odoo_addon_mail_format_with_parent-18.0.1.0.0.dist-info/top_level.txt
odoo_addon_mail_format_with_parent-18.0.1.0.0.dist-info/RECORD
